cooksConnect-Validator/__init__.py
validator/__init__.py
cooksConnect_validator-0.1.dist-info/LICENSE.txt
cooksConnect_validator-0.1.dist-info/METADATA
cooksConnect_validator-0.1.dist-info/WHEEL
cooksConnect_validator-0.1.dist-info/top_level.txt
cooksConnect_validator-0.1.dist-info/RECORD
