Metadata-Version: 2.1
Name: cooksConnect-validator
Version: 0.1
Summary: Validator Package
Home-page: https://github.com/koremanju-coder/cooksConnect
Author: Manjula Kore
Author-email: koremanju00@gmail.com
Classifier: Programming Language :: Python :: 3
Classifier: License :: OSI Approved :: MIT License
Classifier: Operating System :: OS Independent
Requires-Python: >=3.9
License-File: LICENSE.txt
